[{"list":"white","s":"roguejs.com","type":"domain","id":1375211243168},{"list":"white","s":"spiegel.de","type":"domain","id":1375211243169},{"list":"white","s":"stackoverflow.com","type":"domain","id":1375211243170},{"list":"white","s":"heise.de","type":"domain","id":1375211243171},{"list":"white","s":"w3schools.com","type":"domain","id":1375211243172},{"list":"white","s":"zeit.de","type":"domain","id":1375211243173},{"list":"white","s":"sueddeutsche.de","type":"domain","id":1375211243174},{"list":"white","s":"sueddeutsche.com","type":"domain","id":1375211243175},{"list":"white","s":"amazon.de","type":"domain","id":1375211243176},{"list":"white","s":"lovefilm.com","type":"domain","id":1375211243177},{"list":"white","s":"computerbase.de","type":"domain","id":1375211243178},{"list":"white","s":"nodejs.org","type":"domain","id":1375211243179},{"list":"white","s":"fotocommunity.de","type":"domain","id":1375211243180},{"list":"white","s":"fotocommunity.com","type":"domain","id":1375211243181},{"list":"white","s":"macrumors.com","type":"domain","id":1375211243182},{"list":"white","s":"arstechnica.com","type":"domain","id":1375211243183},{"list":"white","s":"arstechnica.net","type":"domain","id":1375211243184},{"list":"white","s":"joeffice.com","type":"domain","id":1375211243185},{"list":"white","s":"handbrake.fr","type":"domain","id":1375211243186},{"list":"white","s":"metronaut.de","type":"domain","id":1375211243187},{"list":"white","s":"fefe.de","type":"domain","id":1375211243188},{"list":"white","s":"dict.cc","type":"domain","id":1375211243189},{"list":"white","s":"anime-loads.org","type":"domain","id":1375211243190},{"list":"white","s":"fotocommunity.net","type":"domain","id":1375211243191},{"list":"white","s":"socket.io","type":"domain","id":1375211243192},{"list":"white","s":"jquery.com","type":"domain","id":1375211243193},{"list":"white","s":"knockoutjs.com","type":"domain","id":1375211243194},{"list":"white","s":"time.com","type":"domain","id":1375211243195},{"list":"white","s":"serienjunkies.org","type":"domain","id":1375211243196},{"list":"white","s":"derstandard.at","type":"domain","id":1375211243197},{"list":"white","s":"uploaded.net","type":"domain","id":1375211243198},{"list":"white","s":"akamaihd.net","type":"domain","id":1375211243199},{"s":"c.spiegel.de","type":"domain","list":"black","id":1375212768699},{"s":"prophet.heise.de","type":"domain","list":"black","id":1375212781307},{"s":"http://www.computerbase.de/stats.php","type":"url","list":"black","id":1375299738618},{"s":"http://m.heise.de/avw-bin","type":"url","list":"black","id":1375299739994}]